{"ongoing_trials": {}, "hyperparameters": {"space": [{"class_name": "Int", "config": {"name": "num_gru_layers", "default": null, "conditions": [], "min_value": 1, "max_value": 3, "step": 1, "sampling": "linear"}}, {"class_name": "Int", "config": {"name": "gru_units_0", "default": null, "conditions": [], "min_value": 32, "max_value": 128, "step": 16, "sampling": "linear"}}, {"class_name": "Float", "config": {"name": "dropout", "default": 0.0, "conditions": [], "min_value": 0.0, "max_value": 0.5, "step": 0.1, "sampling": "linear"}}, {"class_name": "Float", "config": {"name": "learning_rate", "default": 0.0001, "conditions": [], "min_value": 0.0001, "max_value": 0.01, "step": null, "sampling": "log"}}, {"class_name": "Int", "config": {"name": "gru_units_1", "default": null, "conditions": [], "min_value": 32, "max_value": 128, "step": 16, "sampling": "linear"}}], "values": {"num_gru_layers": 1, "gru_units_0": 32, "dropout": 0.0, "learning_rate": 0.0001, "gru_units_1": 32}}, "start_order": ["0", "1", "2", "3", "4"], "end_order": ["0", "1", "2", "3", "4"], "run_times": {"0": 1, "1": 1, "2": 1, "3": 1, "4": 1}, "retry_queue": [], "seed": 9225, "seed_state": 9247, "tried_so_far": ["aefa0e0f4c6772ac783e182878982dfb", "41caf284ee18d454c17a9639923c4a28", "3e59705ea1dd72267253d6fbbcdabdf9", "0d700c4571e368a06a0cc68f14659511", "d02b9965e1fe19b512c28820123b6560"], "id_to_hash": {"0": "3e59705ea1dd72267253d6fbbcdabdf9", "1": "0d700c4571e368a06a0cc68f14659511", "2": "d02b9965e1fe19b512c28820123b6560", "3": "aefa0e0f4c6772ac783e182878982dfb", "4": "41caf284ee18d454c17a9639923c4a28"}, "display": {"search_start": "2025-05-21T22:58:18.367328", "trial_start": {"0": "2025-05-21T22:58:18.367328", "1": "2025-05-21T23:00:11.261148", "2": "2025-05-21T23:01:51.466201", "3": "2025-05-21T23:04:43.618375", "4": "2025-05-21T23:06:40.967239"}, "trial_number": {"0": 1, "1": 2, "2": 3, "3": 4, "4": 5}}}